Workbook

Sheet 1. Supuestos
A1: Gatekeeper — Modelo de 2 planes: GRATIS y PRO
A2: Celdas AMARILLAS = editables. Todo el libro se recalcula solo.
A4: Parámetro | B4: Valor | C4: Unidad | D4: Nota
A5: Moneda e impuestos
A6: Tipo de cambio USD → PEN | B6: 3.75 | C6: S/ por USD | D6: Referencial ago-2026.
A7: IGV | B7: 0.18 | C7: % | D7: El precio de lista lo incluye: no es ingreso tuyo.
A8: Pasarela de pago (solo aplica al plan PRO)
A9: Comisión Culqi — variable | B9: 0.042 | C9: % | D9: 4.20% tarjeta nacional. CONFIRMAR con tu contrato real.
A10: Comisión Culqi — fija | B10: 0.3 | C10: USD | D10: Por transacción.
A11: IGV sobre la comisión | B11: 0.18 | C11: % | D11: La comisión también paga IGV.
A12: ¿Cobras con tarjeta? (1=Culqi / 0=transferencia) | B12: 1 | C12: 1 ó 0 | D12: 0 = cobro anual por transferencia/Yape → comisión CERO.
A13: Plan PRO
A14: Precio del plan PRO | B14: 89 | C14: S/ /mes | D14: PLAN ÚNICO DEFINIDO: S/ 89/mes. La hoja 5 solo muestra sensibilidad.
A15: Residentes por cuenta PRO | B15: 30 | C15: usuarios | D15: ⚠️ NO es un límite: PRO es ilimitado. Es el TAMAÑO PROMEDIO de un cliente, para estimar costos.
A16: Visitas por residente PRO / mes | B16: 8 | C16: visitas | D16: ≈ 2 por semana. Tampoco es un límite: es uso promedio estimado.
A17: Plan GRATIS
A18: Residentes por cuenta GRATIS | B18: 15 | C18: usuarios | D18: Este SÍ es un límite real del plan gratuito.
A19: Visitas por residente GRATIS / mes | B19: 3 | C19: visitas | D19: Menor uso: el gratis se prueba, no se opera a full.
A20: Cuentas GRATIS activas | B20: 100 | C20: cuentas | D20: Cuántos condominios tienes en el plan gratuito.
A21: ¿El gratis envía emails? (1=Sí / 0=No) | B21: 0 | C21: 1 ó 0 | D21: 0 = el residente ve el ingreso EN LA PLATAFORMA (ya implementado).
A22: Publicidad en el plan GRATIS
A23: ¿Activar publicidad? (1=Sí / 0=No) | B23: 1 | C23: 1 ó 0 | D23: Enciende/apaga el ingreso publicitario en todo el modelo.
A24: Vía activa (1=Banner / 2=Patrocinio) | B24: 1 | C24: 1 ó 2 | D24: El video rewarded NO aplica: exige app nativa y Gatekeeper es solo web.
A25: CPM banner (AdSense web) | B25: 0.5 | C25: USD | D25: Rango real Perú 0.30 – 1.00.
A26: Patrocinio local — por espacio | B26: 80 | C26: S/ /mes | D26: Venta directa a un comercio de la zona.
A27: Patrocinadores vendidos | B27: 0 | C27: espacios | D27: Cuántos espacios tienes colocados.
A28: Impresiones por residente / mes | B28: 12 | C28: impresiones | D28: ≈ 4 sesiones × 3 vistas.
A29: Motor de conversión (así el GRATIS genera ingresos)
A30: Tasa de conversión GRATIS → PRO | B30: 0.05 | C30: % | D30: De cada 100 cuentas gratis, cuántas terminan pagando.
A31: Estructura del negocio
A32: Tu sueldo | B32: 500 | C32: S/ /mes | D32: El mayor costo fijo. Es tu decisión.
A33: Marketing pagado | B33: 300 | C33: S/ /mes | D33: Limitado: el canal principal es el plan gratis.
A34: Soporte — valor imputado | B34: 0 | C34: S/ /mes | D34: 0 = lo das tú y no lo cobras. NO sale del banco.

Sheet 2. Infraestructura
A1: Costos fijos de infraestructura
A2: Lo que cuesta tener la plataforma encendida, tengas 1 o 200 clientes.
A4: Servicio | B4: Plan | C4: USD/mes | D4: S//mes | E4: ¿Obligatorio? | F4: Nota
A5: Vercel | B5: Pro | C5: 20 | D5: =C5*'1. Supuestos'!$B$6 | E5: SÍ | F5: Hobby PROHÍBE uso comercial y ya cobras suscripciones. No es negociable.
A6: Neon (PostgreSQL) | B6: Launch | C6: 19 | D6: =C6*'1. Supuestos'!$B$6 | E6: SÍ | F6: Free ya provocó un timeout del cron por autosuspend.
A7: Resend (emails) | B7: Free | C7: 0 | D7: =C7*'1. Supuestos'!$B$6 | E7: Aún no | F7: Free = 3.000 emails/mes ≈ 12 clientes PRO. Ahí recién Pro ($20).
A8: Upstash Redis | B8: Free | C8: 0 | D8: =C8*'1. Supuestos'!$B$6 | E8: Aún no | F8: Rate limiting usa poquísimos comandos.
A9: Sentry | B9: Free | C9: 0 | D9: =C9*'1. Supuestos'!$B$6 | E9: No | F9: Free = 5k errores/mes. No lo actives hasta que quede chico.
A10: Dominio + correo | B10: Cloudflare | C10: 1 | D10: =C10*'1. Supuestos'!$B$6 | E10: SÍ | F10: Anual prorrateado + Email Routing gratis.
A11: TOTAL INFRAESTRUCTURA | C11: =SUM(C5:C10) | D11: =SUM(D5:D10)
A13: • Este total NO crece con cada cliente: es una sola base de datos multi-tenant.
A14: • Apagar Resend/Upstash/Sentry (todos en Free) ahorra S/210/mes respecto a tenerlos en plan pago.

Sheet 3. Costos x Usuario
A1: Cuánto cuesta cada usuario y cada cuenta
A2: El costo marginal real, separando plan GRATIS de plan PRO.
A4: A) COSTO POR RESIDENTE / MES
A5: Concepto | B5: GRATIS | C5: PRO | D5: Cómo se calcula
A6: Emails de notificación | B6: ='1. Supuestos'!$B$19*2*0.0004*'1. Supuestos'!$B$6*'1. Supuestos'!$B$21 | C6: ='1. Supuestos'!$B$16*2*0.0004*'1. Supuestos'!$B$6 | D6: visitas × 2 emails × USD 0.0004. El gratis los tiene apagados.
A7: Compute + base de datos | B7: ='2. Infraestructura'!$C$11/10000*'1. Supuestos'!$B$6 | C7: ='2. Infraestructura'!$C$11/10000*'1. Supuestos'!$B$6 | D7: Infraestructura ÷ 10.000 residentes de base.
A8: COSTO POR RESIDENTE / MES | B8: =SUM(B6:B7) | C8: =SUM(C6:C7)
A10: B) COSTO POR CUENTA (un condominio completo)
A11: Concepto | B11: GRATIS | C11: PRO | D11: Nota
A12: Residentes por cuenta | B12: ='1. Supuestos'!$B$18 | C12: ='1. Supuestos'!$B$15 | D12: Tope del gratis vs. promedio real de un cliente PRO.
A13: COSTO DE LA CUENTA / MES | B13: ='1. Supuestos'!$B$18*'3. Costos x Usuario'!$B$8 | C13: ='1. Supuestos'!$B$15*'3. Costos x Usuario'!$C$8 | D13: Lo que te cuesta servir a un condominio entero durante un mes.
A15: • Una cuenta gratis cuesta menos que un caramelo. La infra NO es tu problema de negocio.
A16: • Tus costos reales son: el sueldo que te pagas, la comisión de la pasarela y tu tiempo.

Sheet 4. Plan GRATIS
A1: Plan GRATIS — qué cuesta y qué genera
A2: El gratis genera ingresos por DOS vías: publicidad (directa) y conversión a PRO (la importante).
A4: A) LO QUE CUESTA TU BASE GRATIS
A5: Concepto | B5: Valor | C5: Unidad | D5: Nota
A6: Cuentas gratis activas | B6: ='1. Supuestos'!$B$20 | C6: cuentas | D6: Editable en la hoja 1.
A7: Costo por cuenta gratis | B7: ='3. Costos x Usuario'!$B$13 | C7: S/ /mes | D7: 15 residentes × costo por residente.
A8: COSTO TOTAL DE TU BASE GRATIS | B8: ='1. Supuestos'!$B$20*'3. Costos x Usuario'!$B$13 | C8: S/ /mes | D8: Este es el gasto real de regalar el producto.
A10: B) VÍA 1 — PUBLICIDAD: las tres opciones, con veredicto honesto
A11: Opción | B11: Ingreso x cuenta | C11: Ingreso TOTAL | D11: ¿Cubre el costo? | E11: Veredicto y por qué
A12: 1. Banner display (AdSense web) | B12: ='1. Supuestos'!$B$28/1000*'1. Supuestos'!$B$25*'1. Supuestos'!$B$6*'1. Supuestos'!$B$18 | C12: =B12*'1. Supuestos'!$B$20 | D12: =IF(C12>='4. Plan GRATIS'!$B$8,"SÍ","NO") | E12: VIABLE HOY — Funciona en web, sin app nativa. Cubre el costo con margen. Contra: abre el CSP y mete scripts de terceros en pantallas con DNI y placas (Ley 29733).
A13: 2. Patrocinio local directo | B13: ='1. Supuestos'!$B$26*'1. Supuestos'!$B$27 | C13: =B13 | D13: =IF(C13>='4. Plan GRATIS'!$B$8,"SÍ","NO") | E13: SIN RIESGO — Sin ad network, sin scripts, sin tracking, CSP intacto. Contra: es venta 1-a-1 tuya, no ingreso pasivo.
A14: El patrocinio es un monto fijo total (no por cuenta); el banner escala con tu base gratis.
A16: INGRESO PUBLICITARIO SEGÚN LA VÍA QUE ELEGISTE | B16: ='1. Supuestos'!$B$23*CHOOSE('1. Supuestos'!$B$24,C12,C13) | E16: Cambia 'Vía activa' en la hoja 1 para comparar. Con 0 en 'Activar publicidad' se apaga.
A18: C) VÍA 2 — CONVERSIÓN A PRO (aquí está el ingreso de verdad)
A19: Concepto | B19: Valor | C19: Unidad | D19: Nota
A20: Tasa de conversión gratis → PRO | B20: ='1. Supuestos'!$B$30 | C20: % | D20: De cada 100 cuentas gratis, cuántas terminan pagando.
A21: Clientes PRO que produce tu base gratis | B21: =ROUND('1. Supuestos'!$B$20*'1. Supuestos'!$B$30,0) | C21: clientes | D21: Cuentas gratis × tasa de conversión.
A22: INGRESO POR CONVERSIÓN | B22: =ROUND('1. Supuestos'!$B$20*'1. Supuestos'!$B$30,0)*'5. Plan PRO'!$B$12 | C22: S/ /mes | D22: Clientes convertidos × contribución de cada uno.
A24: D) BALANCE DEL PLAN GRATIS
A25: Concepto | B25: S/ /mes | C25: Lectura
A26: (+) Ingreso por publicidad | B26: ='4. Plan GRATIS'!$B$16 | C26: Directo, si la activas.
A27: (+) Ingreso por conversión a PRO | B27: ='4. Plan GRATIS'!$B$22 | C27: Indirecto, pero es el grande.
A28: (–) Costo de la base gratis | B28: =-'4. Plan GRATIS'!$B$8 | C28: Lo que te cuesta servirla.
A29: RESULTADO NETO DEL PLAN GRATIS | B29: =SUM(B26:B28) | C29: Si es positivo, el plan gratis GANA dinero.
A30: Retorno por cada sol invertido en el gratis | B30: =('4. Plan GRATIS'!$B$16+'4. Plan GRATIS'!$B$22)/'4. Plan GRATIS'!$B$8 | C30: Cuántas veces recuperas lo que gastas en regalar el producto.
A32: • Respuesta a '¿cómo genero ingresos en el plan gratis?': por conversión. La publicidad es el extra, no el motor.
A33: • Con 100 cuentas gratis y 5% de conversión obtienes 5 clientes PRO. Eso vale mucho más que cualquier CPM.
A34: • Si subes la conversión del 5% al 8%, ganas más que activando publicidad. Optimiza eso primero.
A35: • El video rewarded queda descartado por arquitectura: AdMob exige app nativa y Gatekeeper es solo web.
A36: • El banner SÍ cubre el costo del gratis. La decisión no es de dinero, es qué le hace al producto y al CSP.

Sheet 5. Plan PRO
A1: Plan PRO — cuánto te deja cada cliente
A2: De lo que cobras a lo que realmente entra al negocio.
A4: Concepto | B4: Importe | C4: Nota
A5: Precio de lista | B5: ='1. Supuestos'!$B$14 | C5: Lo que ve el cliente.
A6: (–) IGV incluido | B6: =-('1. Supuestos'!$B$14-'1. Supuestos'!$B$14/(1+'1. Supuestos'!$B$7)) | C6: Va a SUNAT, no es tuyo.
A7: (=) Ingreso neto | B7: ='1. Supuestos'!$B$14/(1+'1. Supuestos'!$B$7) | C7: Lo que factura el negocio.
A8: (–) Comisión de pasarela | B8: =-IF('1. Supuestos'!$B$12=1,('1. Supuestos'!$B$14*'1. Supuestos'!$B$9+'1. Supuestos'!$B$10*'1. Supuestos'!$B$6)*(1+'1. Supuestos'!$B$11),0) | C8: Con transferencia/Yape esto es CERO.
A9: (–) Costo de servirlo | B9: =-'3. Costos x Usuario'!$C$13 | C9: Infraestructura de sus 30 residentes.
A10: (–) Soporte imputado | B10: =-'1. Supuestos'!$B$34 | C10: En 0: lo das tú y no lo cobras.
A11: CONTRIBUCIÓN POR CLIENTE / MES | B11: =B5+B6+B8+B9+B10 | C11: Lo que aporta cada cliente a cubrir tus costos fijos.
A12: Contribución (referencia interna) | B12: =B11 | C12: Celda que usan las hojas 4 y 6. No la muevas.
A13: Margen de contribución | B13: =B11/B5
A15: SENSIBILIDAD DE PRECIO — ¿cuánto debería costar el plan único?
A16: Precio PRO | B16: Contribución | C16: Clientes para cubrir todo | D16: Facturación | E16: Comentario
A17: 49 | B17: =A17/(1+'1. Supuestos'!$B$7)-IF('1. Supuestos'!$B$12=1,(A17*'1. Supuestos'!$B$9+'1. Supuestos'!$B$10*'1. Supuestos'!$B$6)*(1+'1. Supuestos'!$B$11),0)-'3. Costos x Usuario'!$C$13-'1. Supuestos'!$B$34 | C17: =ROUNDUP('6. Punto Equilibrio'!$B$10/B17,0) | D17: =C17*A17 | E17: Muy barato: necesitas casi el doble de clientes para lo mismo.
A18: 69 | B18: =A18/(1+'1. Supuestos'!$B$7)-IF('1. Supuestos'!$B$12=1,(A18*'1. Supuestos'!$B$9+'1. Supuestos'!$B$10*'1. Supuestos'!$B$6)*(1+'1. Supuestos'!$B$11),0)-'3. Costos x Usuario'!$C$13-'1. Supuestos'!$B$34 | C18: =ROUNDUP('6. Punto Equilibrio'!$B$10/B18,0) | D18: =C18*A18 | E18: Entrada agresiva. Útil para arrancar y subir precio después.
A19: 89 | B19: =A19/(1+'1. Supuestos'!$B$7)-IF('1. Supuestos'!$B$12=1,(A19*'1. Supuestos'!$B$9+'1. Supuestos'!$B$10*'1. Supuestos'!$B$6)*(1+'1. Supuestos'!$B$11),0)-'3. Costos x Usuario'!$C$13-'1. Supuestos'!$B$34 | C19: =ROUNDUP('6. Punto Equilibrio'!$B$10/B19,0) | D19: =C19*A19 | E19: El actual. Equilibrio entre volumen y margen.
A20: 99 | B20: =A20/(1+'1. Supuestos'!$B$7)-IF('1. Supuestos'!$B$12=1,(A20*'1. Supuestos'!$B$9+'1. Supuestos'!$B$10*'1. Supuestos'!$B$6)*(1+'1. Supuestos'!$B$11),0)-'3. Costos x Usuario'!$C$13-'1. Supuestos'!$B$34 | C20: =ROUNDUP('6. Punto Equilibrio'!$B$10/B20,0) | D20: =C20*A20 | E20: Cifra redonda, percepción premium. Poca resistencia extra.
A21: 129 | B21: =A21/(1+'1. Supuestos'!$B$7)-IF('1. Supuestos'!$B$12=1,(A21*'1. Supuestos'!$B$9+'1. Supuestos'!$B$10*'1. Supuestos'!$B$6)*(1+'1. Supuestos'!$B$11),0)-'3. Costos x Usuario'!$C$13-'1. Supuestos'!$B$34 | C21: =ROUNDUP('6. Punto Equilibrio'!$B$10/B21,0) | D21: =C21*A21 | E21: Requiere justificar valor: reportes, multi-empresa, soporte.
A23: • El fijo de USD 0.30 de la pasarela castiga los precios bajos: a S/49 te comes proporcionalmente el doble de comisión.
A24: • Cobrar ANUAL por transferencia elimina la comisión completa y te paga 12 meses por adelantado.
A26: ¿HASTA DÓNDE AGUANTA EL PLAN ILIMITADO?
A27: El único costo que crece con el tamaño del cliente son los correos de aviso. Esta tabla muestra qué queda de los S/ 89 según cuántos residentes tenga.
A28: Tamaño del cliente | B28: Correos al mes | C28: Costo de correos | D28: Contribución | E28: Margen
A29: 15 residentes | B29: =15*'1. Supuestos'!$B$16*2 | C29: =15*'1. Supuestos'!$B$16*2*0.0004*'1. Supuestos'!$B$6 | D29: ='1. Supuestos'!$B$14/(1+'1. Supuestos'!$B$7)-IF('1. Supuestos'!$B$12=1,('1. Supuestos'!$B$14*'1. Supuestos'!$B$9+'1. Supuestos'!$B$10*'1. Supuestos'!$B$6)*(1+'1. Supuestos'!$B$11),0)-C29 | E29: =D29/'1. Supuestos'!$B$14
A30: 30 residentes | B30: =30*'1. Supuestos'!$B$16*2 | C30: =30*'1. Supuestos'!$B$16*2*0.0004*'1. Supuestos'!$B$6 | D30: ='1. Supuestos'!$B$14/(1+'1. Supuestos'!$B$7)-IF('1. Supuestos'!$B$12=1,('1. Supuestos'!$B$14*'1. Supuestos'!$B$9+'1. Supuestos'!$B$10*'1. Supuestos'!$B$6)*(1+'1. Supuestos'!$B$11),0)-C30 | E30: =D30/'1. Supuestos'!$B$14
A31: 100 residentes | B31: =100*'1. Supuestos'!$B$16*2 | C31: =100*'1. Supuestos'!$B$16*2*0.0004*'1. Supuestos'!$B$6 | D31: ='1. Supuestos'!$B$14/(1+'1. Supuestos'!$B$7)-IF('1. Supuestos'!$B$12=1,('1. Supuestos'!$B$14*'1. Supuestos'!$B$9+'1. Supuestos'!$B$10*'1. Supuestos'!$B$6)*(1+'1. Supuestos'!$B$11),0)-C31 | E31: =D31/'1. Supuestos'!$B$14
A32: 300 residentes | B32: =300*'1. Supuestos'!$B$16*2 | C32: =300*'1. Supuestos'!$B$16*2*0.0004*'1. Supuestos'!$B$6 | D32: ='1. Supuestos'!$B$14/(1+'1. Supuestos'!$B$7)-IF('1. Supuestos'!$B$12=1,('1. Supuestos'!$B$14*'1. Supuestos'!$B$9+'1. Supuestos'!$B$10*'1. Supuestos'!$B$6)*(1+'1. Supuestos'!$B$11),0)-C32 | E32: =D32/'1. Supuestos'!$B$14
A33: 500 residentes | B33: =500*'1. Supuestos'!$B$16*2 | C33: =500*'1. Supuestos'!$B$16*2*0.0004*'1. Supuestos'!$B$6 | D33: ='1. Supuestos'!$B$14/(1+'1. Supuestos'!$B$7)-IF('1. Supuestos'!$B$12=1,('1. Supuestos'!$B$14*'1. Supuestos'!$B$9+'1. Supuestos'!$B$10*'1. Supuestos'!$B$6)*(1+'1. Supuestos'!$B$11),0)-C33 | E33: =D33/'1. Supuestos'!$B$14
A34: 1.000 residentes | B34: =1000*'1. Supuestos'!$B$16*2 | C34: =1000*'1. Supuestos'!$B$16*2*0.0004*'1. Supuestos'!$B$6 | D34: ='1. Supuestos'!$B$14/(1+'1. Supuestos'!$B$7)-IF('1. Supuestos'!$B$12=1,('1. Supuestos'!$B$14*'1. Supuestos'!$B$9+'1. Supuestos'!$B$10*'1. Supuestos'!$B$6)*(1+'1. Supuestos'!$B$11),0)-C34 | E34: =D34/'1. Supuestos'!$B$14
A36: Residentes necesarios para que un cliente deje de ser rentable | B36: =ROUND(('1. Supuestos'!$B$14/(1+'1. Supuestos'!$B$7)-IF('1. Supuestos'!$B$12=1,('1. Supuestos'!$B$14*'1. Supuestos'!$B$9+'1. Supuestos'!$B$10*'1. Supuestos'!$B$6)*(1+'1. Supuestos'!$B$11),0))/('1. Supuestos'!$B$16*2*0.0004*'1. Supuestos'!$B$6),0) | C36: Un condominio grande en Perú tiene 200-500 residentes.
A38: • ⚠️ Los 30 residentes y las visitas por residente de la hoja 1 NO son límites del plan: son el uso PROMEDIO con el que se estiman los costos. PRO es ilimitado.
A39: • El riesgo del "ilimitado" no es el costo de servidor: es el soporte. Y hoy lo das tú sin cobrarlo.
A40: • Límite operativo a vigilar: Resend Pro son 50.000 correos al mes. Con clientes de 300 residentes caben unos 10.
A41: • Por eso conviene un fair-use de visitas en el contrato: no por dinero, sino para poder decir que no ante un abuso.

Sheet 6. Punto Equilibrio
A1: Punto de equilibrio de caja
A2: Solo cuenta lo que sale del banco. Tu soporte no se cobra, así que no entra.
A4: Concepto | B4: S/ /mes | C4: Nota
A5: Infraestructura | B5: ='2. Infraestructura'!$D$11 | C5: Vercel + Neon + dominio.
A6: Tu sueldo | B6: ='1. Supuestos'!$B$32 | C6: El componente más grande de tu estructura.
A7: Marketing pagado | B7: ='1. Supuestos'!$B$33 | C7: Limitado a propósito.
A8: TOTAL COSTOS FIJOS | B8: =SUM(B5:B7)
A9: (–) Ingreso publicitario del plan gratis | B9: ='4. Plan GRATIS'!$B$16 | C9: Si activaste publicidad, reduce lo que deben cubrir las suscripciones.
A10: NETO A CUBRIR CON SUSCRIPCIONES | B10: =MAX(0,B8-B9)
A12: RESULTADO
A13: Indicador | B13: Valor | C13: Unidad | D13: Lectura
A14: CLIENTES PRO NECESARIOS | B14: =ROUNDUP(B10/'5. Plan PRO'!$B$12,0) | C14: clientes | D14: Este es tu número. Todo lo demás es ruido.
A15: Facturación mensual en ese punto | B15: =ROUNDUP(B10/'5. Plan PRO'!$B$12,0)*'1. Supuestos'!$B$14 | C15: S/ /mes | D15: Lo que verías entrar por suscripciones.
A16: Cuentas gratis necesarias para producirlos | B16: =ROUNDUP(ROUNDUP(B10/'5. Plan PRO'!$B$12,0)/'1. Supuestos'!$B$30,0) | C16: cuentas | D16: Si TODOS tus clientes vinieran del plan gratis, esta es la base que necesitas.
A17: Clientes que ya te produce tu base gratis actual | B17: =ROUND('1. Supuestos'!$B$20*'1. Supuestos'!$B$30,0) | C17: clientes | D17: Compara contra los clientes necesarios: te dice cuánto te falta.
A19: COMPARACIÓN: ¿cuánto aporta cada palanca?
A20: Palanca | B20: Aporte S//mes | C20: Equivale a | D20: Comentario
A21: Publicidad en el gratis (vía elegida) | B21: ='4. Plan GRATIS'!$B$16 | C21: =B21/'5. Plan PRO'!$B$12 | D21: Ingreso directo. Con banner escala con tu base gratis.
A22: Conversión gratis → PRO | B22: ='4. Plan GRATIS'!$B$22 | C22: =B22/'5. Plan PRO'!$B$12 | D22: El motor real del negocio.
A23: Quitar la pasarela (cobro anual) | B23: =IF('1. Supuestos'!$B$12=1,('1. Supuestos'!$B$14*'1. Supuestos'!$B$9+'1. Supuestos'!$B$10*'1. Supuestos'!$B$6)*(1+'1. Supuestos'!$B$11)*ROUNDUP(B10/'5. Plan PRO'!$B$12,0),0) | C23: =B23/'5. Plan PRO'!$B$12 | D23: Ahorro inmediato, sin vender nada más.
A25: • La columna 'Equivale a' traduce cada palanca a clientes PRO. Así comparas peras con peras.
A26: • Si la conversión aporta más que la publicidad, tu esfuerzo va en producto y onboarding, no en anuncios.
