Workbook

Sheet 1. Supuestos
A1: Gatekeeper — Supuestos del modelo
A2: Celdas AMARILLAS = editables. Todo el libro se recalcula solo al cambiarlas.
A4: Parámetro | B4: Valor | C4: Unidad | D4: Fuente / Nota
A5: Moneda e impuestos
A6: Tipo de cambio USD → PEN | B6: 3.75 | C6: S/ por USD | D6: Referencial ago-2026. Ajustar al TC real de tu banco.
A7: IGV | B7: 0.18 | C7: % | D7: Impuesto General a las Ventas (Perú).
A8: ¿El precio de lista INCLUYE IGV? (1=Sí / 0=No) | B8: 1 | C8: 1 ó 0 | D8: Si emites factura y el precio es final al cliente → 1.
A9: Pasarela de pago (Culqi Online)
A10: Comisión Culqi — variable | B10: 0.042 | C10: % | D10: 4.20% tarjeta nacional (CulqiOnline / e-commerce).
A11: Comisión Culqi — fija | B11: 0.3 | C11: USD | D11: USD 0.30 por transacción.
A12: IGV sobre la comisión Culqi | B12: 0.18 | C12: % | D12: La comisión de la pasarela también paga IGV.
A13: Precios de lista (hoy)
A14: Plan Básico | B14: 49 | C14: S/ /mes | D14: 20 residentes · 1 vigilante (LIMITES_PLAN en el código).
A15: Plan Estándar | B15: 89 | C15: S/ /mes | D15: 50 residentes · 3 vigilantes.
A16: Plan Premium | B16: 149 | C16: S/ /mes | D16: Residentes y vigilantes ilimitados.
A17: Perfil de uso de un cliente típico
A18: Residentes por condominio (promedio) | B18: 30 | C18: usuarios | D18: Ajustar según tu cartera real.
A19: Vigilantes por condominio | B19: 2 | C19: usuarios | D19: No generan costo relevante (consultas ligeras).
A20: Visitas por residente / mes | B20: 4 | C20: visitas | D20: ≈ 1 visita por semana.
A21: Emails por visita | B21: 2 | C21: emails | D21: Notificación de INGRESO + notificación de SALIDA.
A22: Costo por email (Resend Pro) | B22: 0.0004 | C22: USD | D22: USD 20 / 50.000 emails.
A23: Base de residentes para prorratear infra | B23: 10000 | C23: usuarios | D23: Escala a la que se reparte el costo fijo.
A24: Plan GRATIS (configuración de costo reducido)
A25: Residentes del plan gratis | B25: 15 | C25: usuarios | D25: Tope del tier gratuito.
A26: Visitas por residente gratis / mes | B26: 3 | C26: visitas | D26: Menor uso: el gratis es de prueba, no operación plena.
A27: Cuentas gratis activas | B27: 100 | C27: cuentas | D27: Cuántos condominios tienes hoy en plan gratuito.
A28: ¿El plan gratis envía emails? (1=Sí / 0=No) | B28: 0 | C28: 1 ó 0 | D28: 0 = se apaga el ÚNICO costo variable real. Es el gate correcto.
A29: Monetización del tier gratis
A30: Patrocinio local — precio por espacio | B30: 80 | C30: S/ /mes | D30: Inmobiliaria, gimnasio o ferretería de la zona. Venta directa tuya.
A31: Patrocinadores activos | B31: 0 | C31: patrocinadores | D31: 0 = DESCARTADO. El tier gratis cuesta céntimos, no necesita financiarse.
A32: CPM ad network (banner) | B32: 0.5 | C32: USD | D32: Referencia para comparar. Rango real Perú 0.30 – 1.00.
A33: CPM video rewarded | B33: 3 | C33: USD | D33: Referencia. Requiere app nativa (AdMob): Gatekeeper es web/PWA.
A34: Impresiones por residente / mes | B34: 12 | C34: impresiones | D34: ≈ 4 sesiones × 3 vistas. La app se usa poco y rápido.
A35: Costos de operación del negocio
A36: Soporte por cliente | B36: 0 | C36: min/mes | D36: 0 = lo das tú y no lo cobras. NO es desembolso: no entra al equilibrio de caja.
A37: Valor de tu hora | B37: 0 | C37: S/ /hora | D37: Solo para valorar tu tiempo si algun dia lo delegas. Hoy en 0.
A38: Sueldo fundador objetivo | B38: 500 | C38: S/ /mes | D38: Lo que necesitas retirar del negocio. Es TU decision, es el mayor costo fijo.
A39: Marketing pagado mensual | B39: 300 | C39: S/ /mes | D39: Limitado a propósito: el canal principal es el tier gratis, no la pauta.

Sheet 2. Infraestructura
A1: Costos fijos de infraestructura
A2: Lo que cuesta tener la plataforma encendida, independiente de cuántos clientes tengas.
A4: Servicio | B4: Plan | C4: USD / mes | D4: S/ / mes | E4: ¿Obligatorio? | F4: Nota
A5: Vercel | B5: Pro | C5: 20 | D5: =C5*'1. Supuestos'!$B$6 | E5: Sí | F5: CRÍTICO: el plan Hobby PROHÍBE uso comercial y Gatekeeper ya cobra suscripciones.
A6: Neon (PostgreSQL) | B6: Launch | C6: 19 | D6: =C6*'1. Supuestos'!$B$6 | E6: Sí | F6: Free ya causó el timeout del cron por autosuspend (30-jun-2026).
A7: Resend (emails) | B7: Free | C7: 0 | D7: =C7*'1. Supuestos'!$B$6 | E7: Aún no | F7: Free = 3.000 emails/mes: aguanta ~12 clientes pagos. Subir a Pro ($20) recién ahí.
A8: Upstash Redis | B8: Free | C8: 0 | D8: =C8*'1. Supuestos'!$B$6 | E8: Aún no | F8: Rate limiting usa poquísimos comandos. El cron keepalive evita que la archiven.
A9: Sentry | B9: Free | C9: 0 | D9: =C9*'1. Supuestos'!$B$6 | E9: No | F9: Free = 5k errores/mes. No lo actives hasta que te quede chico.
A10: Dominio + correo | B10: Cloudflare | C10: 1 | D10: =C10*'1. Supuestos'!$B$6 | E10: Sí | F10: Dominio anual prorrateado + Email Routing (gratis).
A11: TOTAL INFRAESTRUCTURA | C11: =SUM(C5:C10) | D11: =SUM(D5:D10)
A13: Situación actual vs. modelo
A14: • Hoy pagas ≈ S/ 0 porque todo está en free tier. Eso NO es sostenible ni contractualmente seguro (Vercel Hobby).
A15: • Este total es el costo de la plataforma COMPLETA, no por cliente. Con 6 clientes ya está pagada (ver hoja 5).
A16: • La arquitectura es multi-tenant sobre UNA sola base de datos → el costo NO se multiplica por cada condominio nuevo.

Sheet 3. Costo x Usuario
A1: Costo real por usuario y por cliente
A2: Costo marginal: lo que te cuesta de verdad sumar un residente más a la plataforma.
A4: A) COSTO MARGINAL POR RESIDENTE / MES — usuario de pago vs. usuario gratis
A5: Concepto | B5: Usuario PAGO (S/) | C5: Usuario GRATIS (S/) | D5: Cómo se calcula
A6: Emails de notificación (ingreso + salida) | B6: ='1. Supuestos'!$B$20*'1. Supuestos'!$B$21*'1. Supuestos'!$B$22*'1. Supuestos'!$B$6 | C6: ='1. Supuestos'!$B$26*'1. Supuestos'!$B$21*'1. Supuestos'!$B$22*'1. Supuestos'!$B$6*'1. Supuestos'!$B$28 | D6: El gratis NO envía emails → su único costo variable se apaga.
A7: Compute + base de datos prorrateado | B7: ='2. Infraestructura'!$C$11/'1. Supuestos'!$B$23*'1. Supuestos'!$B$6 | C7: ='2. Infraestructura'!$C$11/'1. Supuestos'!$B$23*'1. Supuestos'!$B$6 | D7: Infraestructura total ÷ base de residentes. Igual para ambos.
A8: COSTO MARGINAL POR RESIDENTE / MES | B8: =SUM(B6:B7) | C8: =SUM(C6:C7) | D8: Apagar los emails baja el costo del usuario gratis ~25%.
A10: B) COSTO DE INFRAESTRUCTURA POR CLIENTE (CONDOMINIO)
A11: Concepto | B11: Valor | C11: Unidad | D11: Nota
A12: Residentes por condominio | B12: ='1. Supuestos'!$B$18 | C12: usuarios | D12: Supuesto editable en la hoja 1.
A13: Costo de infraestructura del cliente | B13: ='1. Supuestos'!$B$18*'3. Costo x Usuario'!$B$8 | C13: S/ /mes | D13: Residentes × costo marginal.
A14: Costo de soporte del cliente | B14: ='1. Supuestos'!$B$36/60*'1. Supuestos'!$B$37 | C14: S/ /mes | D14: Minutos de atención × valor de tu hora.
A15: Comisión Culqi (plan Estándar) | B15: =('1. Supuestos'!$B$15*'1. Supuestos'!$B$10+'1. Supuestos'!$B$11*'1. Supuestos'!$B$6)*(1+'1. Supuestos'!$B$12) | C15: S/ /mes | D15: % sobre el cobro + fijo + IGV de la comisión.
A17: C) CÓMO ESCALA (la infra NO crece proporcional a los clientes)
A18: Escala | B18: Condominios | C18: Residentes totales | D18: Infra S//mes | E18: Infra por residente | F18: Nota
A19: Hoy (arranque) | B19: 5 | C19: =B19*'1. Supuestos'!$B$18 | D19: ='2. Infraestructura'!$D$11*1.0 | E19: =D19/C19 | F19: Pagas el fijo completo aunque esté subutilizado.
A20: Tracción inicial | B20: 50 | C20: =B20*'1. Supuestos'!$B$18 | D20: ='2. Infraestructura'!$D$11*1.0 | E20: =D20/C20 | F20: Mismo fijo: la plataforma ni se entera.
A21: Consolidado | B21: 200 | C21: =B21*'1. Supuestos'!$B$18 | D21: ='2. Infraestructura'!$D$11*1.9 | E21: =D21/C21 | F21: Sube Neon (más compute) y Resend (más emails).
A22: Escala | B22: 1000 | C22: =B22*'1. Supuestos'!$B$18 | D22: ='2. Infraestructura'!$D$11*7.0 | E22: =D22/C22 | F22: Ya necesitas tier superior en BD y emails.
A24: • Multiplicar los clientes por 40 (de 5 a 200) solo multiplica la infraestructura por ~2.
A25: • La columna 'Infra por residente' se DERRUMBA al crecer: ese es el apalancamiento del SaaS.
A26: • Tu costo dominante NO es el servidor: es la comisión de Culqi y tu tiempo de soporte.

Sheet 4. Margen x Cliente
A1: Unit economics — cuánto te queda de cada cliente
A2: De S/ 89 de lista, lo que realmente entra al negocio.
A4: Concepto | B4: Básico | C4: Estándar | D4: Premium | E4: Nota
A5: Precio de lista | B5: ='1. Supuestos'!$B$14 | C5: ='1. Supuestos'!$B$15 | D5: ='1. Supuestos'!$B$16 | E5: Precio publicado en la landing.
A6: (–) IGV incluido en el precio | B6: =IF('1. Supuestos'!$B$8=1,B5-B5/(1+'1. Supuestos'!$B$7),0) | C6: =IF('1. Supuestos'!$B$8=1,C5-C5/(1+'1. Supuestos'!$B$7),0) | D6: =IF('1. Supuestos'!$B$8=1,D5-D5/(1+'1. Supuestos'!$B$7),0) | E6: Si el precio incluye IGV, esto NO es tuyo: va a SUNAT.
A7: (=) Ingreso neto | B7: =B5-B6 | C7: =C5-C6 | D7: =D5-D6 | E7: Lo que efectivamente factura el negocio.
A8: (–) Comisión Culqi | B8: =(B5*'1. Supuestos'!$B$10+'1. Supuestos'!$B$11*'1. Supuestos'!$B$6)*(1+'1. Supuestos'!$B$12) | C8: =(C5*'1. Supuestos'!$B$10+'1. Supuestos'!$B$11*'1. Supuestos'!$B$6)*(1+'1. Supuestos'!$B$12) | D8: =(D5*'1. Supuestos'!$B$10+'1. Supuestos'!$B$11*'1. Supuestos'!$B$6)*(1+'1. Supuestos'!$B$12) | E8: 4.20% + USD 0.30, más IGV sobre la comisión.
A9: (–) Infraestructura del cliente | B9: ='3. Costo x Usuario'!$B$13 | C9: ='3. Costo x Usuario'!$B$13 | D9: ='3. Costo x Usuario'!$B$13 | E9: Residentes × costo marginal.
A10: (–) Soporte del cliente (imputado) | B10: ='3. Costo x Usuario'!$B$14 | C10: ='3. Costo x Usuario'!$B$14 | D10: ='3. Costo x Usuario'!$B$14 | E10: Tu tiempo. En 0 porque lo das tú: NO sale del banco.
A11: (=) CONTRIBUCIÓN POR CLIENTE / MES | B11: =B7-B8-B9-B10 | C11: =C7-C8-C9-C10 | D11: =D7-D8-D9-D10 | E11: Lo que aporta cada cliente a cubrir tus costos fijos.
A12: Margen de contribución % | B12: =B11/B5 | C12: =C11/C5 | D12: =D11/D5 | E12: Contribución ÷ precio de lista.
A14: Dato clave
A15: La comisión de Culqi por UN cobro cuesta más que toda la infraestructura de ese cliente durante el mes.
A16: Si negocias una comisión menor o cobras anual (1 cobro en vez de 12), recuperas margen directo.

Sheet 5. Punto Equilibrio
A1: Punto de equilibrio
A2: Cuántos clientes pagos necesitas para no perder dinero, según qué quieras cubrir.
A4: Escenario | B4: Costos fijos S//mes | C4: (–) Patrocinios | D4: Neto a cubrir | E4: Contribución x cliente | F4: CLIENTES | G4: Qué significa
A5: A) Solo mantener la plataforma | B5: ='2. Infraestructura'!$D$11 | C5: ='1. Supuestos'!$B$30*'1. Supuestos'!$B$31 | D5: =MAX(0,B5-C5) | E5: ='4. Margen x Cliente'!$C$11 | F5: =ROUNDUP(D5/E5,0) | G5: Cubres servidores. No te pagas nada. Mínimo para no perder plata.
A6: B) Plataforma + tu sueldo | B6: ='2. Infraestructura'!$D$11+'1. Supuestos'!$B$38 | C6: ='1. Supuestos'!$B$30*'1. Supuestos'!$B$31 | D6: =MAX(0,B6-C6) | E6: ='4. Margen x Cliente'!$C$11 | F6: =ROUNDUP(D6/E6,0) | G6: Vives del negocio. Este es el objetivo real de corto plazo.
A7: C) Plataforma + sueldo + marketing limitado | B7: ='2. Infraestructura'!$D$11+'1. Supuestos'!$B$38+'1. Supuestos'!$B$39 | C7: ='1. Supuestos'!$B$30*'1. Supuestos'!$B$31 | D7: =MAX(0,B7-C7) | E7: ='4. Margen x Cliente'!$C$11 | F7: =ROUNDUP(D7/E7,0) | G7: Pauta acotada: el canal principal es el tier gratis, no el gasto.
A9: Sensibilidad: ¿y si vendes otro plan?
A10: Plan | B10: Precio | C10: Contribución | D10: Clientes para escenario B | E10: Facturación
A11: Básico | B11: ='1. Supuestos'!$B$14 | C11: ='4. Margen x Cliente'!$B$11 | D11: =ROUNDUP('5. Punto Equilibrio'!$D$6/C11,0) | E11: =D11*B11
A12: Estándar | B12: ='1. Supuestos'!$B$15 | C12: ='4. Margen x Cliente'!$C$11 | D12: =ROUNDUP('5. Punto Equilibrio'!$D$6/C12,0) | E12: =D12*B12
A13: Premium | B13: ='1. Supuestos'!$B$16 | C13: ='4. Margen x Cliente'!$D$11 | D13: =ROUNDUP('5. Punto Equilibrio'!$D$6/C13,0) | E13: =D13*B13
A15: Lectura del resultado
A16: • Los patrocinios locales se restan de los costos fijos: no son un negocio aparte, son un descuento sobre tu estructura.
A17: • El salto real es el escenario B: ahí dejas de subsidiar el proyecto con tu tiempo.
A18: • Vender Básico en vez de Estándar casi TRIPLICA los clientes que necesitas: el fijo de Culqi (USD 0.30) pesa mucho en tickets bajos.
A19: • Por eso conviene empujar Estándar/Premium y no competir por precio en el plan de entrada.
A20: • El marketing pagado está limitado a propósito: con un tier gratis funcionando, el producto es el canal.
A21: • Este es el equilibrio DE CAJA: solo cuenta lo que sale del banco (infra + Culqi + tu sueldo). Tu soporte no se cobra.
A22: • El sueldo es el 77% de tu estructura fija. Es la palanca que mueve el numero, no los servidores.

Sheet 6. Tier Gratis
A1: Cómo se paga el plan gratis
A2: El tier gratis es un canal de adquisición. La pregunta es qué cubre su costo sin dañar el producto.
A4: A) CUÁNTO CUESTA REALMENTE UN CONDOMINIO EN PLAN GRATIS
A5: Concepto | B5: Valor | C5: Unidad | E5: Cómo se calcula
A6: Residentes por cuenta gratis | B6: ='1. Supuestos'!$B$25 | C6: usuarios | E6: Tope del plan gratuito.
A7: Costo marginal por residente gratis | B7: ='3. Costo x Usuario'!$C$8 | C7: S/ /mes | E7: Sin emails: solo compute + base de datos.
A8: COSTO TOTAL DE UNA CUENTA GRATIS | B8: ='1. Supuestos'!$B$25*'3. Costo x Usuario'!$C$8 | C8: S/ /mes | E8: Lo que te cuesta regalar el producto a un condominio entero.
A9: Cuentas gratis que financia 1 patrocinador local | B9: =ROUNDDOWN('1. Supuestos'!$B$30/('1. Supuestos'!$B$25*'3. Costo x Usuario'!$C$8),0) | C9: cuentas | E9: Patrocinio ÷ costo de una cuenta gratis.
A11: B) LAS TRES VÍAS PARA MONETIZAR EL GRATIS — comparación directa
A12: Vía | B12: Ingreso S//mes | C12: ¿Cubre el costo? | D12: Veredicto | E12: Por qué
A13: 1. Banner de ad network (AdSense) | B13: ='1. Supuestos'!$B$34/1000*'1. Supuestos'!$B$32*'1. Supuestos'!$B$6*'1. Supuestos'!$B$25 | C13: =IF(B13>='6. Tier Gratis'!$B$8,"SÍ","NO") | D13: DESCARTADO | E13: Ni siquiera paga el hosting. Además abre el CSP y mete scripts de terceros junto a DNI y placas.
A14: 2. Video rewarded (AdMob) | B14: ='1. Supuestos'!$B$34/1000*'1. Supuestos'!$B$33*'1. Supuestos'!$B$6*'1. Supuestos'!$B$25 | C14: =IF(B14>='6. Tier Gratis'!$B$8,"SÍ","NO") | D14: INVIABLE | E14: Empata, pero AdMob exige app nativa y Gatekeeper es web/PWA. Y frena al residente justo en la puerta.
A15: 3. Patrocinio local directo | B15: ='1. Supuestos'!$B$30 | C15: =IF(B15>='6. Tier Gratis'!$B$8,"SÍ","NO") | D15: NO NECESARIO | E15: Funciona, pero es un segundo negocio (venta 1-a-1). Por lo que cuesta el tier gratis, no vale tu tiempo.
A16: Nota: las vías 1 y 2 se calculan sobre los 15 residentes de UNA cuenta gratis, para comparar contra su costo real.
A18: C) ESCALA DEL PATROCINIO — cuánta gratuidad puedes sostener
A19: Concepto | B19: Valor | C19: Unidad | E19: Nota
A20: Ingreso total por patrocinios | B20: ='1. Supuestos'!$B$30*'1. Supuestos'!$B$31 | C20: S/ /mes | E20: Espacios vendidos × precio. Se resta de tus costos fijos (hoja 5).
A21: Usuarios gratis que financia | B21: =ROUNDDOWN('1. Supuestos'!$B$30*'1. Supuestos'!$B$31/'3. Costo x Usuario'!$C$8,0) | C21: usuarios | E21: Capacidad de gratuidad totalmente pagada.
A22: Condominios gratis que financia | B22: =ROUNDDOWN('1. Supuestos'!$B$30*'1. Supuestos'!$B$31/('1. Supuestos'!$B$25*'3. Costo x Usuario'!$C$8),0) | C22: condominios | E22: Cuentas gratis sostenidas sin tocar tu bolsillo.
A23: Costo de TU base gratis actual | B23: ='1. Supuestos'!$B$27*'1. Supuestos'!$B$25*'3. Costo x Usuario'!$C$8 | C23: S/ /mes | E23: Cuentas gratis activas × 15 residentes × costo por residente. Este es el gasto real.
A24: CLIENTES PAGOS QUE LA FINANCIAN | B24: =ROUNDUP('1. Supuestos'!$B$27*'1. Supuestos'!$B$25*'3. Costo x Usuario'!$C$8/'4. Margen x Cliente'!$C$11,0) | C24: clientes | E24: Cuántos clientes de pago hacen falta para cubrir TODA tu gratuidad. Suele ser 1.
A25: Cuentas gratis que financia 1 cliente pago | B25: =ROUNDDOWN('4. Margen x Cliente'!$C$11/('1. Supuestos'!$B$25*'3. Costo x Usuario'!$C$8),0) | C25: cuentas | E25: La cifra clave: el tier gratis se paga solo con un puñado de clientes.
A28: D) ESTRUCTURA DE PLANES — el gate limita VOLUMEN, nunca capacidades
A29: Característica | B29: GRATIS | C29: PRO (S/ 89 – 129) | E29: Por qué ese límite
A30: Residentes | B30: 15 | C30: Ilimitados | E30: Volumen. Costo marginal ≈ S/ 0.036 → 'ilimitado' no te cuesta y vende.
A31: Vigilantes | B31: 1 | C31: Ilimitados | E31: Volumen. El 2º vigilante es lo que necesita un coworking.
A32: Visitas por mes | B32: 50 | C32: 3.000 (fair use) | E32: Volumen. El tope NO es por costo: es contra el abuso y el soporte.
A33: Ver ingreso/salida EN LA PLATAFORMA | B33: SÍ | C33: SÍ | E33: CAPACIDAD. El residente ve 'Llegó 15:42' en su panel e historial. Nunca se limita.
A34: Aviso por email (ingreso/salida) | B34: NO | C34: SÍ | E34: Comodidad, no información: el dato ya está en la plataforma. Además libera el límite de Resend Free.
A35: Reportes y exportación | B35: NO | C35: SÍ | E35: Valor puro para el administrador, costo cero para ti.
A36: Historial | B36: 30 días | C36: Completo | E36: Volumen de almacenamiento. El historial es la 'prueba' que vende.
A37: Empresas (multi-organización) | B37: SÍ | C37: SÍ | E37: CAPACIDAD, no volumen. Define A QUIÉN sirves: bloquearla mata el segmento y no ahorra nada.
A38: Escaneo QR, placa/DNI, roles | B38: SÍ | C38: SÍ | E38: CAPACIDAD. Es el producto. Nunca se limita.
A39: Publicidad de terceros | B39: Ninguna | C39: Ninguna | E39: Solo patrocinio local propio, sin ad network ni scripts externos.
A41: E) LA REGLA
A42: • Limita VOLUMEN (residentes, visitas, historial) y lo que CUESTA DINERO (emails). Nunca capacidades estructurales.
A43: • Bloquear 'empresas' en el gratis no reduce ningún costo: impide que entren las administradoras y los coworking, que son el segmento que quieres.
A44: • En usuarios del plan pago: sin límite. No cuesta nada y 'ilimitado' cierra ventas.
A45: • En visitas y emails del plan pago: fair use (~3.000/mes). No por servidor, sino porque una cuenta con 40 edificios consume el soporte de 40 clientes pagando uno.
A46: • Cada edificio con su propia cuenta y su propio administrador: autónomo, aislado por RLS y facturable por separado.
